jit_pack/__init__.py
jit_pack/jit_auth.py
jit_pack/jit_client.py
jit_pack/jit_message.py
jit_pack/jit_orders.py
jitPack-0.1.dist-info/LICENSE
jitPack-0.1.dist-info/METADATA
jitPack-0.1.dist-info/WHEEL
jitPack-0.1.dist-info/top_level.txt
jitPack-0.1.dist-info/RECORD
