Metadata-Version: 2.1
Name: jitPack
Version: 0.1
Summary: A Python package to facilitate the interaction with JIT_API
Author: zouhir dev
Classifier: Programming Language :: Python :: 3
Classifier: License :: OSI Approved :: MIT License
Classifier: Operating System :: OS Independent
Requires-Python: >=3.6
License-File: LICENSE
Requires-Dist: fastapi==0.115.2
Requires-Dist: uvicorn==0.32.0
Requires-Dist: Rx==3.2.0
Requires-Dist: requests==2.32.3
Requires-Dist: keyring==25.4.1
Requires-Dist: jsonschema==4.23.0
Requires-Dist: pydantic==2.9.2
